setup.py
tfslib.py
tfslib.egg-info/PKG-INFO
tfslib.egg-info/SOURCES.txt
tfslib.egg-info/dependency_links.txt
tfslib.egg-info/requires.txt
tfslib.egg-info/top_level.txt