Metadata-Version: 1.1
Name: tfslib
Version: 0.1.2
Summary: Python client for Microsoft TFS issue tracker.
Home-page: https://bitbucket.org/volodymyr_buell/python-tfs
Author: Volodymyr Buell
Author-email: vbuell@gmail.com
License: APL2
Keywords: TFS tracker issue python client
Platform: UNKNOWN
Classifier: Development Status :: 3 - Alpha
Classifier: License :: OSI Approved :: Apache Software License
Classifier: Topic :: Software Development :: Libraries :: Python Modules
